{
   "bestStep" : 0,
   "bestTime" : 0,
   "solutions" : [
      {
         "bin" : 0,
         "height" : 33,
         "id" : "15",
         "width" : 23,
         "x" : 0,
         "y" : 0
      },
      {
         "bin" : 0,
         "height" : 32,
         "id" : "12",
         "width" : 30,
         "x" : 0,
         "y" : 33
      },
      {
         "bin" : 0,
         "height" : 30,
         "id" : "1",
         "width" : 15,
         "x" : 23,
         "y" : 0
      },
      {
         "bin" : 0,
         "height" : 2,
         "id" : "14",
         "width" : 8,
         "x" : 23,
         "y" : 30
      },
      {
         "bin" : 0,
         "height" : 29,
         "id" : "4",
         "width" : 12,
         "x" : 0,
         "y" : 65
      },
      {
         "bin" : 0,
         "height" : 5,
         "id" : "17",
         "width" : 15,
         "x" : 0,
         "y" : 94
      },
      {
         "bin" : 0,
         "height" : 27,
         "id" : "20",
         "width" : 23,
         "x" : 12,
         "y" : 65
      },
      {
         "bin" : 0,
         "height" : 7,
         "id" : "5",
         "width" : 2,
         "x" : 15,
         "y" : 92
      },
      {
         "bin" : 0,
         "height" : 7,
         "id" : "3",
         "width" : 27,
         "x" : 17,
         "y" : 92
      },
      {
         "bin" : 0,
         "height" : 21,
         "id" : "8",
         "width" : 2,
         "x" : 30,
         "y" : 32
      },
      {
         "bin" : 0,
         "height" : 12,
         "id" : "16",
         "width" : 23,
         "x" : 30,
         "y" : 53
      },
      {
         "bin" : 0,
         "height" : 19,
         "id" : "11",
         "width" : 4,
         "x" : 32,
         "y" : 30
      },
      {
         "bin" : 0,
         "height" : 4,
         "id" : "19",
         "width" : 31,
         "x" : 32,
         "y" : 49
      },
      {
         "bin" : 0,
         "height" : 19,
         "id" : "18",
         "width" : 19,
         "x" : 36,
         "y" : 30
      },
      {
         "bin" : 0,
         "height" : 19,
         "id" : "6",
         "width" : 14,
         "x" : 35,
         "y" : 65
      },
      {
         "bin" : 0,
         "height" : 16,
         "id" : "9",
         "width" : 4,
         "x" : 44,
         "y" : 84
      },
      {
         "bin" : 0,
         "height" : 13,
         "id" : "2",
         "width" : 3,
         "x" : 48,
         "y" : 84
      },
      {
         "bin" : 0,
         "height" : 17,
         "id" : "10",
         "width" : 14,
         "x" : 49,
         "y" : 65
      },
      {
         "bin" : 0,
         "height" : 13,
         "id" : "7",
         "width" : 12,
         "x" : 51,
         "y" : 82
      },
      {
         "bin" : 0,
         "height" : 5,
         "id" : "13",
         "width" : 17,
         "x" : 51,
         "y" : 95
      }
   ],
   "unity" : 0.51590000000000003
}

