{
   "bestStep" : 16949,
   "bestTime" : 685,
   "solutions" : [
      {
         "bin" : 0,
         "height" : 96,
         "id" : "6",
         "width" : 15,
         "x" : 0,
         "y" : 0
      },
      {
         "bin" : 0,
         "height" : 4,
         "id" : "9",
         "width" : 24,
         "x" : 0,
         "y" : 96
      },
      {
         "bin" : 0,
         "height" : 2,
         "id" : "12",
         "width" : 76,
         "x" : 24,
         "y" : 0
      },
      {
         "bin" : 0,
         "height" : 94,
         "id" : "39",
         "width" : 35,
         "x" : 15,
         "y" : 2
      },
      {
         "bin" : 0,
         "height" : 19,
         "id" : "28",
         "width" : 44,
         "x" : 50,
         "y" : 2
      },
      {
         "bin" : 0,
         "height" : 79,
         "id" : "15",
         "width" : 44,
         "x" : 50,
         "y" : 21
      },
      {
         "bin" : 0,
         "height" : 91,
         "id" : "20",
         "width" : 6,
         "x" : 94,
         "y" : 2
      },
      {
         "bin" : 1,
         "height" : 81,
         "id" : "24",
         "width" : 45,
         "x" : 0,
         "y" : 0
      },
      {
         "bin" : 1,
         "height" : 89,
         "id" : "30",
         "width" : 24,
         "x" : 45,
         "y" : 0
      },
      {
         "bin" : 1,
         "height" : 90,
         "id" : "25",
         "width" : 18,
         "x" : 69,
         "y" : 0
      },
      {
         "bin" : 1,
         "height" : 92,
         "id" : "7",
         "width" : 7,
         "x" : 87,
         "y" : 0
      },
      {
         "bin" : 1,
         "height" : 76,
         "id" : "3",
         "width" : 6,
         "x" : 94,
         "y" : 0
      },
      {
         "bin" : 2,
         "height" : 48,
         "id" : "34",
         "width" : 41,
         "x" : 0,
         "y" : 0
      },
      {
         "bin" : 2,
         "height" : 85,
         "id" : "27",
         "width" : 37,
         "x" : 41,
         "y" : 0
      },
      {
         "bin" : 2,
         "height" : 41,
         "id" : "22",
         "width" : 24,
         "x" : 0,
         "y" : 48
      },
      {
         "bin" : 2,
         "height" : 71,
         "id" : "1",
         "width" : 22,
         "x" : 78,
         "y" : 0
      },
      {
         "bin" : 2,
         "height" : 28,
         "id" : "40",
         "width" : 14,
         "x" : 78,
         "y" : 71
      },
      {
         "bin" : 2,
         "height" : 38,
         "id" : "10",
         "width" : 12,
         "x" : 24,
         "y" : 48
      },
      {
         "bin" : 3,
         "height" : 87,
         "id" : "37",
         "width" : 49,
         "x" : 0,
         "y" : 0
      },
      {
         "bin" : 3,
         "height" : 81,
         "id" : "29",
         "width" : 34,
         "x" : 49,
         "y" : 0
      },
      {
         "bin" : 3,
         "height" : 83,
         "id" : "5",
         "width" : 17,
         "x" : 83,
         "y" : 0
      },
      {
         "bin" : 4,
         "height" : 87,
         "id" : "26",
         "width" : 18,
         "x" : 0,
         "y" : 0
      },
      {
         "bin" : 4,
         "height" : 83,
         "id" : "35",
         "width" : 41,
         "x" : 18,
         "y" : 0
      },
      {
         "bin" : 4,
         "height" : 81,
         "id" : "11",
         "width" : 20,
         "x" : 59,
         "y" : 0
      },
      {
         "bin" : 4,
         "height" : 75,
         "id" : "4",
         "width" : 21,
         "x" : 79,
         "y" : 0
      },
      {
         "bin" : 5,
         "height" : 97,
         "id" : "13",
         "width" : 43,
         "x" : 0,
         "y" : 0
      },
      {
         "bin" : 5,
         "height" : 96,
         "id" : "14",
         "width" : 21,
         "x" : 43,
         "y" : 0
      },
      {
         "bin" : 5,
         "height" : 84,
         "id" : "19",
         "width" : 30,
         "x" : 64,
         "y" : 0
      },
      {
         "bin" : 5,
         "height" : 84,
         "id" : "32",
         "width" : 6,
         "x" : 94,
         "y" : 0
      },
      {
         "bin" : 5,
         "height" : 14,
         "id" : "16",
         "width" : 30,
         "x" : 64,
         "y" : 84
      },
      {
         "bin" : 6,
         "height" : 98,
         "id" : "23",
         "width" : 28,
         "x" : 0,
         "y" : 0
      },
      {
         "bin" : 6,
         "height" : 2,
         "id" : "8",
         "width" : 74,
         "x" : 0,
         "y" : 98
      },
      {
         "bin" : 6,
         "height" : 98,
         "id" : "17",
         "width" : 23,
         "x" : 28,
         "y" : 0
      },
      {
         "bin" : 6,
         "height" : 98,
         "id" : "36",
         "width" : 29,
         "x" : 51,
         "y" : 0
      },
      {
         "bin" : 6,
         "height" : 82,
         "id" : "38",
         "width" : 20,
         "x" : 80,
         "y" : 0
      },
      {
         "bin" : 6,
         "height" : 10,
         "id" : "21",
         "width" : 15,
         "x" : 80,
         "y" : 82
      },
      {
         "bin" : 7,
         "height" : 73,
         "id" : "18",
         "width" : 42,
         "x" : 0,
         "y" : 0
      },
      {
         "bin" : 7,
         "height" : 74,
         "id" : "2",
         "width" : 29,
         "x" : 42,
         "y" : 0
      },
      {
         "bin" : 7,
         "height" : 80,
         "id" : "33",
         "width" : 10,
         "x" : 71,
         "y" : 0
      },
      {
         "bin" : 7,
         "height" : 80,
         "id" : "31",
         "width" : 8,
         "x" : 81,
         "y" : 0
      }
   ],
   "steps" : [
      0,
      1,
      2,
      4,
      8,
      37,
      40,
      157,
      543,
      567,
      568,
      576,
      580,
      673,
      714,
      862,
      3789,
      16949
   ],
   "times" : [ 0, 0, 0, 0, 0, 1, 1, 4, 14, 15, 15, 15, 15, 19, 20, 26, 143, 685 ],
   "unity" : 7.6652000000000005,
   "unitys" : [
      8.4940004348754883,
      8.4680004119873047,
      8.4040002822875977,
      8.3769998550415039,
      8.255000114440918,
      8.1969995498657227,
      8.1560001373291016,
      8.0799999237060547,
      7.7639999389648438,
      7.7630000114440918,
      7.7519998550415039,
      7.7389998435974121,
      7.7170000076293945,
      7.7129998207092285,
      7.6830000877380371,
      7.6789999008178711,
      7.6719999313354492,
      7.6649999618530273
   ]
}

