{
   "bestStep" : 6581,
   "bestTime" : 120,
   "solutions" : [
      {
         "bin" : 0,
         "height" : 5,
         "id" : "47",
         "width" : 10,
         "x" : 0,
         "y" : 0
      },
      {
         "bin" : 0,
         "height" : 2,
         "id" : "76",
         "width" : 10,
         "x" : 0,
         "y" : 5
      },
      {
         "bin" : 0,
         "height" : 3,
         "id" : "46",
         "width" : 9,
         "x" : 0,
         "y" : 7
      },
      {
         "bin" : 1,
         "height" : 6,
         "id" : "66",
         "width" : 6,
         "x" : 0,
         "y" : 0
      },
      {
         "bin" : 1,
         "height" : 4,
         "id" : "7",
         "width" : 3,
         "x" : 0,
         "y" : 6
      },
      {
         "bin" : 1,
         "height" : 3,
         "id" : "65",
         "width" : 4,
         "x" : 6,
         "y" : 0
      },
      {
         "bin" : 1,
         "height" : 2,
         "id" : "19",
         "width" : 6,
         "x" : 3,
         "y" : 6
      },
      {
         "bin" : 1,
         "height" : 3,
         "id" : "21",
         "width" : 4,
         "x" : 6,
         "y" : 3
      },
      {
         "bin" : 1,
         "height" : 2,
         "id" : "40",
         "width" : 6,
         "x" : 3,
         "y" : 8
      },
      {
         "bin" : 2,
         "height" : 2,
         "id" : "17",
         "width" : 9,
         "x" : 0,
         "y" : 0
      },
      {
         "bin" : 2,
         "height" : 8,
         "id" : "1",
         "width" : 5,
         "x" : 0,
         "y" : 2
      },
      {
         "bin" : 2,
         "height" : 7,
         "id" : "78",
         "width" : 5,
         "x" : 5,
         "y" : 2
      },
      {
         "bin" : 3,
         "height" : 8,
         "id" : "2",
         "width" : 8,
         "x" : 0,
         "y" : 0
      },
      {
         "bin" : 3,
         "height" : 2,
         "id" : "24",
         "width" : 9,
         "x" : 0,
         "y" : 8
      },
      {
         "bin" : 4,
         "height" : 9,
         "id" : "53",
         "width" : 9,
         "x" : 0,
         "y" : 0
      },
      {
         "bin" : 4,
         "height" : 1,
         "id" : "51",
         "width" : 6,
         "x" : 0,
         "y" : 9
      },
      {
         "bin" : 5,
         "height" : 10,
         "id" : "73",
         "width" : 5,
         "x" : 0,
         "y" : 0
      },
      {
         "bin" : 5,
         "height" : 10,
         "id" : "36",
         "width" : 5,
         "x" : 5,
         "y" : 0
      },
      {
         "bin" : 6,
         "height" : 10,
         "id" : "61",
         "width" : 10,
         "x" : 0,
         "y" : 0
      },
      {
         "bin" : 7,
         "height" : 10,
         "id" : "27",
         "width" : 10,
         "x" : 0,
         "y" : 0
      },
      {
         "bin" : 8,
         "height" : 7,
         "id" : "43",
         "width" : 10,
         "x" : 0,
         "y" : 0
      },
      {
         "bin" : 8,
         "height" : 3,
         "id" : "20",
         "width" : 10,
         "x" : 0,
         "y" : 7
      },
      {
         "bin" : 9,
         "height" : 10,
         "id" : "30",
         "width" : 6,
         "x" : 0,
         "y" : 0
      },
      {
         "bin" : 9,
         "height" : 9,
         "id" : "49",
         "width" : 4,
         "x" : 6,
         "y" : 0
      },
      {
         "bin" : 10,
         "height" : 9,
         "id" : "75",
         "width" : 10,
         "x" : 0,
         "y" : 0
      },
      {
         "bin" : 10,
         "height" : 1,
         "id" : "50",
         "width" : 7,
         "x" : 0,
         "y" : 9
      },
      {
         "bin" : 10,
         "height" : 1,
         "id" : "58",
         "width" : 3,
         "x" : 7,
         "y" : 9
      },
      {
         "bin" : 11,
         "height" : 9,
         "id" : "15",
         "width" : 10,
         "x" : 0,
         "y" : 0
      },
      {
         "bin" : 11,
         "height" : 1,
         "id" : "72",
         "width" : 10,
         "x" : 0,
         "y" : 9
      },
      {
         "bin" : 12,
         "height" : 9,
         "id" : "38",
         "width" : 3,
         "x" : 0,
         "y" : 0
      },
      {
         "bin" : 12,
         "height" : 8,
         "id" : "29",
         "width" : 6,
         "x" : 3,
         "y" : 0
      },
      {
         "bin" : 12,
         "height" : 2,
         "id" : "10",
         "width" : 6,
         "x" : 3,
         "y" : 8
      },
      {
         "bin" : 12,
         "height" : 7,
         "id" : "3",
         "width" : 1,
         "x" : 9,
         "y" : 0
      },
      {
         "bin" : 13,
         "height" : 6,
         "id" : "56",
         "width" : 7,
         "x" : 0,
         "y" : 0
      },
      {
         "bin" : 13,
         "height" : 9,
         "id" : "57",
         "width" : 3,
         "x" : 7,
         "y" : 0
      },
      {
         "bin" : 13,
         "height" : 2,
         "id" : "42",
         "width" : 7,
         "x" : 0,
         "y" : 6
      },
      {
         "bin" : 13,
         "height" : 2,
         "id" : "16",
         "width" : 7,
         "x" : 0,
         "y" : 8
      },
      {
         "bin" : 14,
         "height" : 7,
         "id" : "9",
         "width" : 9,
         "x" : 0,
         "y" : 0
      },
      {
         "bin" : 14,
         "height" : 3,
         "id" : "68",
         "width" : 5,
         "x" : 0,
         "y" : 7
      },
      {
         "bin" : 14,
         "height" : 3,
         "id" : "34",
         "width" : 5,
         "x" : 5,
         "y" : 7
      },
      {
         "bin" : 14,
         "height" : 5,
         "id" : "25",
         "width" : 1,
         "x" : 9,
         "y" : 0
      },
      {
         "bin" : 15,
         "height" : 7,
         "id" : "28",
         "width" : 7,
         "x" : 0,
         "y" : 0
      },
      {
         "bin" : 15,
         "height" : 10,
         "id" : "63",
         "width" : 3,
         "x" : 7,
         "y" : 0
      },
      {
         "bin" : 15,
         "height" : 3,
         "id" : "69",
         "width" : 5,
         "x" : 0,
         "y" : 7
      },
      {
         "bin" : 15,
         "height" : 3,
         "id" : "71",
         "width" : 1,
         "x" : 5,
         "y" : 7
      },
      {
         "bin" : 15,
         "height" : 3,
         "id" : "22",
         "width" : 1,
         "x" : 6,
         "y" : 7
      },
      {
         "bin" : 16,
         "height" : 4,
         "id" : "59",
         "width" : 10,
         "x" : 0,
         "y" : 0
      },
      {
         "bin" : 16,
         "height" : 6,
         "id" : "4",
         "width" : 6,
         "x" : 0,
         "y" : 4
      },
      {
         "bin" : 16,
         "height" : 6,
         "id" : "18",
         "width" : 4,
         "x" : 6,
         "y" : 4
      },
      {
         "bin" : 17,
         "height" : 6,
         "id" : "26",
         "width" : 8,
         "x" : 0,
         "y" : 0
      },
      {
         "bin" : 17,
         "height" : 4,
         "id" : "23",
         "width" : 6,
         "x" : 0,
         "y" : 6
      },
      {
         "bin" : 17,
         "height" : 4,
         "id" : "41",
         "width" : 3,
         "x" : 6,
         "y" : 6
      },
      {
         "bin" : 17,
         "height" : 4,
         "id" : "74",
         "width" : 2,
         "x" : 8,
         "y" : 0
      },
      {
         "bin" : 18,
         "height" : 9,
         "id" : "44",
         "width" : 8,
         "x" : 0,
         "y" : 0
      },
      {
         "bin" : 18,
         "height" : 9,
         "id" : "67",
         "width" : 1,
         "x" : 8,
         "y" : 0
      },
      {
         "bin" : 18,
         "height" : 1,
         "id" : "32",
         "width" : 9,
         "x" : 0,
         "y" : 9
      },
      {
         "bin" : 18,
         "height" : 7,
         "id" : "48",
         "width" : 1,
         "x" : 9,
         "y" : 0
      },
      {
         "bin" : 18,
         "height" : 3,
         "id" : "55",
         "width" : 1,
         "x" : 9,
         "y" : 7
      },
      {
         "bin" : 19,
         "height" : 9,
         "id" : "70",
         "width" : 5,
         "x" : 0,
         "y" : 0
      },
      {
         "bin" : 19,
         "height" : 6,
         "id" : "52",
         "width" : 5,
         "x" : 5,
         "y" : 0
      },
      {
         "bin" : 19,
         "height" : 4,
         "id" : "60",
         "width" : 5,
         "x" : 5,
         "y" : 6
      },
      {
         "bin" : 20,
         "height" : 7,
         "id" : "37",
         "width" : 8,
         "x" : 0,
         "y" : 0
      },
      {
         "bin" : 20,
         "height" : 3,
         "id" : "62",
         "width" : 10,
         "x" : 0,
         "y" : 7
      },
      {
         "bin" : 20,
         "height" : 4,
         "id" : "79",
         "width" : 1,
         "x" : 8,
         "y" : 0
      },
      {
         "bin" : 21,
         "height" : 10,
         "id" : "31",
         "width" : 8,
         "x" : 0,
         "y" : 0
      },
      {
         "bin" : 21,
         "height" : 8,
         "id" : "80",
         "width" : 2,
         "x" : 8,
         "y" : 0
      },
      {
         "bin" : 22,
         "height" : 9,
         "id" : "33",
         "width" : 8,
         "x" : 0,
         "y" : 0
      },
      {
         "bin" : 22,
         "height" : 2,
         "id" : "6",
         "width" : 2,
         "x" : 8,
         "y" : 0
      },
      {
         "bin" : 22,
         "height" : 1,
         "id" : "39",
         "width" : 8,
         "x" : 0,
         "y" : 9
      },
      {
         "bin" : 22,
         "height" : 5,
         "id" : "5",
         "width" : 1,
         "x" : 8,
         "y" : 2
      },
      {
         "bin" : 22,
         "height" : 5,
         "id" : "45",
         "width" : 1,
         "x" : 9,
         "y" : 2
      },
      {
         "bin" : 23,
         "height" : 6,
         "id" : "77",
         "width" : 9,
         "x" : 0,
         "y" : 0
      },
      {
         "bin" : 23,
         "height" : 4,
         "id" : "8",
         "width" : 9,
         "x" : 0,
         "y" : 6
      },
      {
         "bin" : 24,
         "height" : 5,
         "id" : "35",
         "width" : 8,
         "x" : 0,
         "y" : 0
      },
      {
         "bin" : 24,
         "height" : 5,
         "id" : "54",
         "width" : 7,
         "x" : 0,
         "y" : 5
      },
      {
         "bin" : 24,
         "height" : 3,
         "id" : "11",
         "width" : 3,
         "x" : 7,
         "y" : 5
      },
      {
         "bin" : 24,
         "height" : 3,
         "id" : "12",
         "width" : 2,
         "x" : 8,
         "y" : 0
      },
      {
         "bin" : 24,
         "height" : 2,
         "id" : "14",
         "width" : 3,
         "x" : 7,
         "y" : 8
      },
      {
         "bin" : 25,
         "height" : 9,
         "id" : "64",
         "width" : 3,
         "x" : 0,
         "y" : 0
      },
      {
         "bin" : 25,
         "height" : 2,
         "id" : "13",
         "width" : 3,
         "x" : 3,
         "y" : 0
      }
   ],
   "steps" : [
      29,
      78,
      185,
      262,
      270,
      271,
      273,
      288,
      290,
      305,
      310,
      323,
      348,
      362,
      405,
      414,
      652,
      655,
      837,
      905,
      1846,
      1863,
      1872,
      1883,
      5010,
      6581
   ],
   "times" : [
      0,
      1,
      3,
      4,
      4,
      4,
      4,
      5,
      5,
      5,
      5,
      5,
      6,
      6,
      7,
      7,
      11,
      11,
      14,
      16,
      33,
      34,
      34,
      34,
      92,
      120
   ],
   "unity" : 25.329999999999998,
   "unitys" : [
      27.420000076293945,
      27.350000381469727,
      27.299999237060547,
      27.139999389648438,
      27.100000381469727,
      27.090000152587891,
      26.719999313354492,
      26.620000839233398,
      26.559999465942383,
      26.5,
      26.360000610351562,
      26.329999923706055,
      26.270000457763672,
      26.209999084472656,
      26.200000762939453,
      26.120000839233398,
      26.069999694824219,
      25.719999313354492,
      25.649999618530273,
      25.520000457763672,
      25.479999542236328,
      25.469999313354492,
      25.459999084472656,
      25.399999618530273,
      25.389999389648438,
      25.329999923706055
   ]
}

